django_safe_emailbackend-1.2.8.dist-info/licenses/LICENSE
saferecipient/VERSION
saferecipient/__init__.py
saferecipient/tests.py
django_safe_emailbackend-1.2.8.dist-info/METADATA
django_safe_emailbackend-1.2.8.dist-info/WHEEL
django_safe_emailbackend-1.2.8.dist-info/top_level.txt
django_safe_emailbackend-1.2.8.dist-info/RECORD
